twinleaf-0.1.3.dist-info/METADATA
twinleaf-0.1.3.dist-info/WHEEL
twinleaf-0.1.3.dist-info/entry_points.txt
twinleaf-0.1.3.dist-info/licenses/LICENSE-APACHE.txt
twinleaf-0.1.3.dist-info/licenses/LICENSE-MIT.txt
twinleaf/__init__.py
twinleaf/_twinleaf.cp311-win_amd64.pyd
twinleaf/itl.py
twinleaf-0.1.3.dist-info/RECORD
