Metadata-Version: 2.4
Name: twinleaf
Version: 0.1.3
Classifier: Topic :: System :: Hardware :: Hardware Drivers
Classifier: Topic :: Scientific/Engineering :: Physics
Classifier: Topic :: Scientific/Engineering :: Interface Engine/Protocol Translator
Classifier: Programming Language :: Rust
Classifier: Programming Language :: Python :: Implementation :: CPython
Classifier: Programming Language :: Python :: Implementation :: PyPy
Classifier: License :: OSI Approved :: MIT License
Classifier: License :: OSI Approved :: Apache Software License
Requires-Dist: ipython>=9
License-File: LICENSE-APACHE.txt
License-File: LICENSE-MIT.txt
Summary: Communications library and utilities for Twinleaf I/O (TIO) devices
Requires-Python: >=3.10
